{
  "image_size": {
    "width": 1122,
    "height": 1298
  },
  "scale": 1.0,
  "summary": {
    "wires": 54,
    "wire_chains": 5,
    "dashed_regions": 14,
    "slider_terminals": 1
  },
  "wires": [
    {
      "x1": 419,
      "y1": 2,
      "x2": 518,
      "y2": 2,
      "length": 99.0,
      "angle": 0.0,
      "orientation": "horizontal"
    },
    {
      "x1": 571,
      "y1": 2,
      "x2": 637,
      "y2": 2,
      "length": 66.0,
      "angle": 0.0,
      "orientation": "horizontal"
    },
    {
      "x1": 632,
      "y1": 23,
      "x2": 743,
      "y2": 23,
      "length": 111.0,
      "angle": 0.0,
      "orientation": "horizontal"
    },
    {
      "x1": 407,
      "y1": 46,
      "x2": 518,
      "y2": 46,
      "length": 111.0,
      "angle": 0.0,
      "orientation": "horizontal"
    },
    {
      "x1": 571,
      "y1": 46,
      "x2": 635,
      "y2": 46,
      "length": 64.0,
      "angle": 0.0,
      "orientation": "horizontal"
    },
    {
      "x1": 632,
      "y1": 69,
      "x2": 743,
      "y2": 69,
      "length": 111.0,
      "angle": 0.0,
      "orientation": "horizontal"
    },
    {
      "x1": 407,
      "y1": 91,
      "x2": 518,
      "y2": 91,
      "length": 111.0,
      "angle": 0.0,
      "orientation": "horizontal"
    },
    {
      "x1": 571,
      "y1": 91,
      "x2": 637,
      "y2": 91,
      "length": 66.0,
      "angle": 0.0,
      "orientation": "horizontal"
    },
    {
      "x1": 632,
      "y1": 111,
      "x2": 743,
      "y2": 111,
      "length": 111.0,
      "angle": 0.0,
      "orientation": "horizontal"
    },
    {
      "x1": 277,
      "y1": 134,
      "x2": 518,
      "y2": 134,
      "length": 241.0,
      "angle": 0.0,
      "orientation": "horizontal"
    },
    {
      "x1": 572,
      "y1": 134,
      "x2": 637,
      "y2": 134,
      "length": 65.0,
      "angle": 0.0,
      "orientation": "horizontal"
    },
    {
      "x1": 633,
      "y1": 156,
      "x2": 743,
      "y2": 156,
      "length": 110.0,
      "angle": 0.0,
      "orientation": "horizontal"
    },
    {
      "x1": 629,
      "y1": 392,
      "x2": 752,
      "y2": 392,
      "length": 123.0,
      "angle": 0.0,
      "orientation": "horizontal"
    },
    {
      "x1": 268,
      "y1": 412,
      "x2": 509,
      "y2": 412,
      "length": 241.0,
      "angle": 0.0,
      "orientation": "horizontal"
    },
    {
      "x1": 550,
      "y1": 412,
      "x2": 636,
      "y2": 412,
      "length": 86.0,
      "angle": 0.0,
      "orientation": "horizontal"
    },
    {
      "x1": 628,
      "y1": 433,
      "x2": 752,
      "y2": 433,
      "length": 124.0,
      "angle": 0.0,
      "orientation": "horizontal"
    },
    {
      "x1": 432,
      "y1": 456,
      "x2": 522,
      "y2": 456,
      "length": 90.0,
      "angle": 0.0,
      "orientation": "horizontal"
    },
    {
      "x1": 550,
      "y1": 456,
      "x2": 622,
      "y2": 456,
      "length": 72.0,
      "angle": 0.0,
      "orientation": "horizontal"
    },
    {
      "x1": 629,
      "y1": 480,
      "x2": 752,
      "y2": 480,
      "length": 123.0,
      "angle": 0.0,
      "orientation": "horizontal"
    },
    {
      "x1": 388,
      "y1": 501,
      "x2": 522,
      "y2": 501,
      "length": 134.0,
      "angle": 0.0,
      "orientation": "horizontal"
    },
    {
      "x1": 555,
      "y1": 501,
      "x2": 622,
      "y2": 501,
      "length": 67.0,
      "angle": 0.0,
      "orientation": "horizontal"
    },
    {
      "x1": 629,
      "y1": 522,
      "x2": 752,
      "y2": 522,
      "length": 123.0,
      "angle": 0.0,
      "orientation": "horizontal"
    },
    {
      "x1": 435,
      "y1": 546,
      "x2": 516,
      "y2": 546,
      "length": 81.0,
      "angle": 0.0,
      "orientation": "horizontal"
    },
    {
      "x1": 555,
      "y1": 546,
      "x2": 628,
      "y2": 546,
      "length": 73.0,
      "angle": 0.0,
      "orientation": "horizontal"
    },
    {
      "x1": 629,
      "y1": 568,
      "x2": 752,
      "y2": 568,
      "length": 123.0,
      "angle": 0.0,
      "orientation": "horizontal"
    },
    {
      "x1": 389,
      "y1": 589,
      "x2": 516,
      "y2": 589,
      "length": 127.0,
      "angle": 0.0,
      "orientation": "horizontal"
    },
    {
      "x1": 549,
      "y1": 589,
      "x2": 636,
      "y2": 589,
      "length": 87.0,
      "angle": 0.0,
      "orientation": "horizontal"
    },
    {
      "x1": 629,
      "y1": 613,
      "x2": 752,
      "y2": 613,
      "length": 123.0,
      "angle": 0.0,
      "orientation": "horizontal"
    },
    {
      "x1": 433,
      "y1": 634,
      "x2": 522,
      "y2": 634,
      "length": 89.0,
      "angle": 0.0,
      "orientation": "horizontal"
    },
    {
      "x1": 549,
      "y1": 634,
      "x2": 628,
      "y2": 634,
      "length": 79.0,
      "angle": 0.0,
      "orientation": "horizontal"
    },
    {
      "x1": 629,
      "y1": 655,
      "x2": 752,
      "y2": 655,
      "length": 123.0,
      "angle": 0.0,
      "orientation": "horizontal"
    },
    {
      "x1": 390,
      "y1": 679,
      "x2": 530,
      "y2": 679,
      "length": 140.0,
      "angle": 0.0,
      "orientation": "horizontal"
    },
    {
      "x1": 562,
      "y1": 679,
      "x2": 636,
      "y2": 679,
      "length": 74.0,
      "angle": 0.0,
      "orientation": "horizontal"
    },
    {
      "x1": 629,
      "y1": 700,
      "x2": 752,
      "y2": 700,
      "length": 123.0,
      "angle": 0.0,
      "orientation": "horizontal"
    },
    {
      "x1": 268,
      "y1": 722,
      "x2": 509,
      "y2": 722,
      "length": 241.0,
      "angle": 0.0,
      "orientation": "horizontal"
    },
    {
      "x1": 629,
      "y1": 745,
      "x2": 752,
      "y2": 745,
      "length": 123.0,
      "angle": 0.0,
      "orientation": "horizontal"
    },
    {
      "x1": 628,
      "y1": 788,
      "x2": 752,
      "y2": 788,
      "length": 124.0,
      "angle": 0.0,
      "orientation": "horizontal"
    },
    {
      "x1": 641,
      "y1": 799,
      "x2": 735,
      "y2": 799,
      "length": 94.0,
      "angle": 0.0,
      "orientation": "horizontal"
    },
    {
      "x1": 628,
      "y1": 842,
      "x2": 752,
      "y2": 842,
      "length": 124.0,
      "angle": 0.0,
      "orientation": "horizontal"
    },
    {
      "x1": 628,
      "y1": 888,
      "x2": 752,
      "y2": 888,
      "length": 124.0,
      "angle": 0.0,
      "orientation": "horizontal"
    },
    {
      "x1": 628,
      "y1": 930,
      "x2": 752,
      "y2": 930,
      "length": 124.0,
      "angle": 0.0,
      "orientation": "horizontal"
    },
    {
      "x1": 628,
      "y1": 976,
      "x2": 752,
      "y2": 976,
      "length": 124.0,
      "angle": 0.0,
      "orientation": "horizontal"
    },
    {
      "x1": 628,
      "y1": 1018,
      "x2": 752,
      "y2": 1018,
      "length": 124.0,
      "angle": 0.0,
      "orientation": "horizontal"
    },
    {
      "x1": 376,
      "y1": 412,
      "x2": 376,
      "y2": 669,
      "length": 257.0,
      "angle": 90.0,
      "orientation": "vertical"
    },
    {
      "x1": 408,
      "y1": 13,
      "x2": 408,
      "y2": 127,
      "length": 114.0,
      "angle": 90.0,
      "orientation": "vertical"
    },
    {
      "x1": 421,
      "y1": 470,
      "x2": 421,
      "y2": 725,
      "length": 255.0,
      "angle": 90.0,
      "orientation": "vertical"
    },
    {
      "x1": 623,
      "y1": 390,
      "x2": 623,
      "y2": 1023,
      "length": 633.0,
      "angle": 90.0,
      "orientation": "vertical"
    },
    {
      "x1": 632,
      "y1": 0,
      "x2": 632,
      "y2": 186,
      "length": 186.0,
      "angle": 90.0,
      "orientation": "vertical"
    },
    {
      "x1": 632,
      "y1": 365,
      "x2": 632,
      "y2": 1023,
      "length": 658.0,
      "angle": 90.0,
      "orientation": "vertical"
    },
    {
      "x1": 726,
      "y1": 655,
      "x2": 726,
      "y2": 802,
      "length": 147.0,
      "angle": 90.0,
      "orientation": "vertical"
    },
    {
      "x1": 726,
      "y1": 841,
      "x2": 726,
      "y2": 1022,
      "length": 181.0,
      "angle": 90.0,
      "orientation": "vertical"
    },
    {
      "x1": 738,
      "y1": 0,
      "x2": 738,
      "y2": 186,
      "length": 186.0,
      "angle": 90.0,
      "orientation": "vertical"
    },
    {
      "x1": 738,
      "y1": 365,
      "x2": 738,
      "y2": 1023,
      "length": 658.0,
      "angle": 90.0,
      "orientation": "vertical"
    },
    {
      "x1": 747,
      "y1": 390,
      "x2": 747,
      "y2": 1023,
      "length": 633.0,
      "angle": 90.0,
      "orientation": "vertical"
    }
  ],
  "wire_chains": [
    {
      "chain_id": 0,
      "wire_indices": [
        0,
        44,
        3,
        6,
        9
      ]
    },
    {
      "chain_id": 1,
      "wire_indices": [
        1,
        47,
        2,
        4,
        5,
        7,
        8,
        10,
        11,
        51
      ]
    },
    {
      "chain_id": 2,
      "wire_indices": [
        12,
        46,
        53,
        48,
        52,
        42,
        14,
        15,
        17,
        18,
        20,
        21,
        23,
        24,
        26,
        27,
        29,
        30,
        32,
        33,
        35,
        36,
        38,
        39,
        40,
        41,
        37,
        50,
        49
      ]
    },
    {
      "chain_id": 3,
      "wire_indices": [
        13,
        43,
        19,
        25,
        31
      ]
    },
    {
      "chain_id": 4,
      "wire_indices": [
        16,
        45,
        22,
        28,
        34
      ]
    }
  ],
  "dashed_regions": [
    {
      "x": 268,
      "y": 710,
      "width": 241,
      "height": 30
    },
    {
      "x": 434,
      "y": 635,
      "width": 88,
      "height": 1
    },
    {
      "x": 389,
      "y": 471,
      "width": 141,
      "height": 242
    },
    {
      "x": 433,
      "y": 457,
      "width": 89,
      "height": 2
    },
    {
      "x": 377,
      "y": 424,
      "width": 2,
      "height": 245
    },
    {
      "x": 268,
      "y": 400,
      "width": 241,
      "height": 30
    },
    {
      "x": 550,
      "y": 366,
      "width": 237,
      "height": 657
    },
    {
      "x": 277,
      "y": 122,
      "width": 241,
      "height": 30
    },
    {
      "x": 422,
      "y": 91,
      "width": 96,
      "height": 2
    },
    {
      "x": 421,
      "y": 47,
      "width": 97,
      "height": 1
    },
    {
      "x": 408,
      "y": 14,
      "width": 2,
      "height": 113
    },
    {
      "x": 420,
      "y": 2,
      "width": 98,
      "height": 2
    },
    {
      "x": 1121,
      "y": 0,
      "width": 1,
      "height": 1298
    },
    {
      "x": 572,
      "y": 0,
      "width": 206,
      "height": 186
    }
  ],
  "slider_rects": [
    {
      "x": 635,
      "y": 791,
      "width": 105,
      "height": 52,
      "has_slider": true
    }
  ]
}